9-s complement of bcd 4 digit/16CO138-VD1.v
//DATAFLOW

module complement(a,b,c,d,w,x,y,z);
   
    input a,b,c,d;
	output w,x,y,z;
	wire w1,w2,w3,w4;
	
	assign z=~d;
	assign y=c;
	assign w=~(a|b|c);
	assign w1=~a;
	assign w2=b^c;
	assign x=w1 & w2;
	
endmodule

9-s complement of bcd 4 digit/16CO138-V1.v
//testbench

`timescale 1ns/1ps
module inp;
     reg a,b,c,d;
	 wire w,x,y,z;
	 
	 complement out(.a(a),.b(b),.c(c),.d(d),.w(w),.x(x),.y(y),.z(z));
	 
	 initial
	 begin
	      $monitor("w x y z\n");
		  $dumpfile("16CO138-V1.vcd");
		  $dumpvars(0,inp);
		  
		  a=1'b0;
		b=1'b0;
		c=1'b0;
		d=1'b0;
		$monitor(w,x,y,z,"\n");
		
#10;
		a=1'b0;
		b=1'b0;
		c=1'b0;
		d=1'b1;
		$monitor(w,x,y,z,"\n");

#10;
		a=1'b0;
		b=1'b0;
		c=1'b1;
		d=1'b0;
		$monitor(w,x,y,z,"\n");

#10;		
		a=1'b0;
		b=1'b0;
		c=1'b1;
		d=1'b1;
		$monitor(w,x,y,z,"\n");

#10;		
		a=1'b0;
		b=1'b1;
		c=1'b0;
		d=1'b0;
		$monitor(w,x,y,z,"\n");

#10;
		a=1'b0;
		b=1'b1;
		c=1'b0;
		d=1'b1;
		$monitor(w,x,y,z,"\n");

#10;
		a=1'b0;
		b=1'b1;
		c=1'b1;
		d=1'b0;
		$monitor(w,x,y,z,"\n");

#10;
		a=1'b0;
		b=1'b1;
		c=1'b1;
		d=1'b1;
		$monitor(w,x,y,z,"\n");

#10;
		a=1'b1;
		b=1'b0;
		c=1'b0;
		d=1'b0;
		$monitor(w,x,y,z,"\n");

#10;
		a=1'b1;
		b=1'b0;
		c=1'b0;
		d=1'b1;
		$monitor(w,x,y,z,"\n");
	end
	initial #300 $finish;
endmodule

9-s complement of bcd 4 digit/16CO138-V1.vcd
$date
	Sat Nov 11 11:21:20 2017
$end
$version
	Icarus Verilog
$end
$timescale
	1ps
$end
$scope module inp $end
$var wire 1 ! z $end
$var wire 1 " y $end
$var wire 1 # x $end
$var wire 1 $ w $end
$var reg 1 % a $end
$var reg 1 & b $end
$var reg 1 ' c $end
$var reg 1 ( d $end
$scope module out $end
$var wire 1 % a $end
$var wire 1 & b $end
$var wire 1 ' c $end
$var wire 1 ( d $end
$var wire 1 $ w $end
$var wire 1 ) w1 $end
$var wire 1 * w2 $end
$var wire 1 + w3 $end
$var wire 1 , w4 $end
$var wire 1 # x $end
$var wire 1 " y $end
$var wire 1 ! z $end
$upscope $end
$upscope $end
$enddefinitions $end
#0
$dumpvars
0,
1+
1*
1)
0(
0'
0&
0%
1$
0#
0"
1!
$end
#10000
0!
1(
#20000
0$
1#
1!
1"
0+
1,
0(
1'
#30000
0!
1(
#40000
1!
0"
1+
0*
0(
0'
1&
#50000
0!
1(
#60000
0#
1!
1"
0+
0,
0(
1'
#70000
0!
1(
#80000
1!
0"
1+
1*
0)
0(
0'
0&
1%
#90000
0!
1(
